<?xml version="1.0" encoding="UTF-8" standalone="no"?><Gesture Name="circle08" Subject="2" number="8"><Point T="1678331934" X="235.0" Y="141.0"/><Point T="1678331934" X="235.0" Y="141.0"/><Point T="1678331934" X="233.0" Y="141.0"/><Point T="1678331934" X="231.0" Y="141.0"/><Point T="1678331934" X="228.0" Y="142.0"/><Point T="1678331934" X="225.0" Y="143.0"/><Point T="1678331934" X="221.0" Y="145.0"/><Point T="1678331934" X="216.0" Y="148.0"/><Point T="1678331934" X="210.0" Y="152.0"/><Point T="1678331934" X="203.0" Y="158.0"/><Point T="1678331934" X="193.0" Y="167.0"/><Point T="1678331934" X="182.0" Y="178.0"/><Point T="1678331934" X="172.0" Y="188.0"/><Point T="1678331934" X="164.0" Y="196.0"/><Point T="1678331934" X="159.0" Y="204.0"/><Point T="1678331934" X="155.0" Y="210.0"/><Point T="1678331934" X="153.0" Y="216.0"/><Point T="1678331934" X="152.0" Y="221.0"/><Point T="1678331934" X="152.0" Y="226.0"/><Point T="1678331934" X="152.0" Y="232.0"/><Point T="1678331934" X="152.0" Y="237.0"/><Point T="1678331934" X="152.0" Y="242.0"/><Point T="1678331934" X="153.0" Y="247.0"/><Point T="1678331934" X="154.0" Y="251.0"/><Point T="1678331934" X="158.0" Y="257.0"/><Point T="1678331934" X="162.0" Y="264.0"/><Point T="1678331934" X="168.0" Y="273.0"/><Point T="1678331934" X="175.0" Y="282.0"/><Point T="1678331934" X="181.0" Y="290.0"/><Point T="1678331934" X="188.0" Y="299.0"/><Point T="1678331934" X="196.0" Y="307.0"/><Point T="1678331934" X="203.0" Y="313.0"/><Point T="1678331934" X="211.0" Y="318.0"/><Point T="1678331934" X="219.0" Y="323.0"/><Point T="1678331934" X="227.0" Y="327.0"/><Point T="1678331934" X="237.0" Y="330.0"/><Point T="1678331934" X="248.0" Y="333.0"/><Point T="1678331934" X="261.0" Y="336.0"/><Point T="1678331934" X="274.0" Y="338.0"/><Point T="1678331934" X="286.0" Y="339.0"/><Point T="1678331934" X="296.0" Y="340.0"/><Point T="1678331934" X="307.0" Y="340.0"/><Point T="1678331934" X="317.0" Y="340.0"/><Point T="1678331934" X="324.0" Y="338.0"/><Point T="1678331934" X="330.0" Y="335.0"/><Point T="1678331934" X="335.0" Y="332.0"/><Point T="1678331934" X="339.0" Y="328.0"/><Point T="1678331934" X="342.0" Y="323.0"/><Point T="1678331934" X="345.0" Y="317.0"/><Point T="1678331934" X="348.0" Y="309.0"/><Point T="1678331934" X="351.0" Y="299.0"/><Point T="1678331934" X="353.0" Y="291.0"/><Point T="1678331934" X="355.0" Y="282.0"/><Point T="1678331934" X="356.0" Y="272.0"/><Point T="1678331934" X="357.0" Y="262.0"/><Point T="1678331934" X="357.0" Y="252.0"/><Point T="1678331934" X="357.0" Y="242.0"/><Point T="1678331934" X="356.0" Y="234.0"/><Point T="1678331934" X="355.0" Y="226.0"/><Point T="1678331934" X="353.0" Y="217.0"/><Point T="1678331934" X="351.0" Y="209.0"/><Point T="1678331934" X="349.0" Y="203.0"/><Point T="1678331934" X="346.0" Y="196.0"/><Point T="1678331934" X="344.0" Y="190.0"/><Point T="1678331934" X="341.0" Y="184.0"/><Point T="1678331934" X="338.0" Y="180.0"/><Point T="1678331934" X="335.0" Y="176.0"/><Point T="1678331934" X="333.0" Y="172.0"/><Point T="1678331934" X="330.0" Y="169.0"/><Point T="1678331934" X="326.0" Y="166.0"/><Point T="1678331934" X="322.0" Y="163.0"/><Point T="1678331934" X="318.0" Y="161.0"/><Point T="1678331934" X="315.0" Y="159.0"/><Point T="1678331934" X="311.0" Y="157.0"/><Point T="1678331934" X="307.0" Y="156.0"/><Point T="1678331934" X="304.0" Y="155.0"/><Point T="1678331934" X="300.0" Y="155.0"/><Point T="1678331934" X="297.0" Y="154.0"/><Point T="1678331934" X="293.0" Y="154.0"/><Point T="1678331934" X="291.0" Y="154.0"/><Point T="1678331934" X="288.0" Y="153.0"/><Point T="1678331934" X="285.0" Y="152.0"/><Point T="1678331934" X="283.0" Y="151.0"/><Point T="1678331934" X="280.0" Y="151.0"/><Point T="1678331934" X="278.0" Y="150.0"/><Point T="1678331934" X="276.0" Y="149.0"/><Point T="1678331934" X="274.0" Y="149.0"/><Point T="1678331934" X="272.0" Y="149.0"/><Point T="1678331934" X="270.0" Y="148.0"/><Point T="1678331934" X="268.0" Y="148.0"/><Point T="1678331934" X="266.0" Y="147.0"/><Point T="1678331934" X="264.0" Y="146.0"/><Point T="1678331934" X="262.0" Y="145.0"/><Point T="1678331934" X="260.0" Y="145.0"/><Point T="1678331934" X="258.0" Y="144.0"/><Point T="1678331934" X="256.0" Y="144.0"/><Point T="1678331934" X="254.0" Y="143.0"/><Point T="1678331934" X="252.0" Y="142.0"/><Point T="1678331934" X="250.0" Y="142.0"/><Point T="1678331934" X="249.0" Y="141.0"/><Point T="1678331934" X="247.0" Y="141.0"/><Point T="1678331934" X="245.0" Y="140.0"/><Point T="1678331934" X="243.0" Y="140.0"/><Point T="1678331934" X="242.0" Y="139.0"/><Point T="1678331934" X="240.0" Y="139.0"/><Point T="1678331934" X="238.0" Y="139.0"/><Point T="1678331934" X="237.0" Y="139.0"/><Point T="1678331934" X="236.0" Y="139.0"/><Point T="1678331934" X="235.0" Y="139.0"/><Point T="1678331934" X="234.0" Y="139.0"/><Point T="1678331934" X="233.0" Y="139.0"/></Gesture>