<?xml version="1.0" encoding="UTF-8" standalone="no"?><Gesture Name="x04" Subject="1" number="4"><Point T="1678331165" X="139.0" Y="212.0"/><Point T="1678331165" X="139.0" Y="212.0"/><Point T="1678331165" X="141.0" Y="216.0"/><Point T="1678331165" X="148.0" Y="225.0"/><Point T="1678331165" X="159.0" Y="238.0"/><Point T="1678331165" X="172.0" Y="253.0"/><Point T="1678331165" X="185.0" Y="269.0"/><Point T="1678331165" X="195.0" Y="281.0"/><Point T="1678331165" X="202.0" Y="289.0"/><Point T="1678331165" X="208.0" Y="296.0"/><Point T="1678331165" X="212.0" Y="300.0"/><Point T="1678331165" X="215.0" Y="303.0"/><Point T="1678331165" X="217.0" Y="304.0"/><Point T="1678331165" X="218.0" Y="305.0"/><Point T="1678331165" X="219.0" Y="306.0"/><Point T="1678331165" X="219.0" Y="306.0"/><Point T="1678331165" X="220.0" Y="306.0"/><Point T="1678331165" X="220.0" Y="306.0"/><Point T="1678331165" X="221.0" Y="304.0"/><Point T="1678331165" X="221.0" Y="301.0"/><Point T="1678331165" X="222.0" Y="295.0"/><Point T="1678331165" X="222.0" Y="289.0"/><Point T="1678331165" X="222.0" Y="281.0"/><Point T="1678331165" X="222.0" Y="272.0"/><Point T="1678331165" X="222.0" Y="262.0"/><Point T="1678331165" X="222.0" Y="253.0"/><Point T="1678331165" X="222.0" Y="244.0"/><Point T="1678331165" X="222.0" Y="237.0"/><Point T="1678331165" X="222.0" Y="232.0"/><Point T="1678331165" X="222.0" Y="230.0"/><Point T="1678331165" X="222.0" Y="228.0"/><Point T="1678331165" X="222.0" Y="227.0"/><Point T="1678331165" X="221.0" Y="227.0"/><Point T="1678331165" X="221.0" Y="226.0"/><Point T="1678331165" X="221.0" Y="226.0"/><Point T="1678331165" X="220.0" Y="225.0"/><Point T="1678331165" X="220.0" Y="225.0"/><Point T="1678331165" X="219.0" Y="225.0"/><Point T="1678331165" X="218.0" Y="226.0"/><Point T="1678331165" X="217.0" Y="227.0"/><Point T="1678331165" X="216.0" Y="229.0"/><Point T="1678331165" X="214.0" Y="231.0"/><Point T="1678331165" X="210.0" Y="235.0"/><Point T="1678331165" X="205.0" Y="241.0"/><Point T="1678331165" X="200.0" Y="247.0"/><Point T="1678331165" X="194.0" Y="253.0"/><Point T="1678331165" X="189.0" Y="257.0"/><Point T="1678331165" X="184.0" Y="260.0"/><Point T="1678331165" X="177.0" Y="265.0"/><Point T="1678331165" X="165.0" Y="274.0"/><Point T="1678331165" X="150.0" Y="285.0"/><Point T="1678331165" X="135.0" Y="296.0"/><Point T="1678331165" X="122.0" Y="306.0"/><Point T="1678331165" X="113.0" Y="312.0"/><Point T="1678331165" X="108.0" Y="315.0"/><Point T="1678331165" X="106.0" Y="316.0"/><Point T="1678331165" X="106.0" Y="316.0"/><Point T="1678331165" X="106.0" Y="315.0"/><Point T="1678331165" X="106.0" Y="314.0"/><Point T="1678331165" X="106.0" Y="312.0"/><Point T="1678331165" X="106.0" Y="311.0"/><Point T="1678331165" X="107.0" Y="310.0"/><Point T="1678331165" X="107.0" Y="309.0"/></Gesture>